nemony/__init__.py
nemony/cli.py
nemony/nemony.py
nemony/words.yml
nemony-0.0.2.dist-info/LICENSE
nemony-0.0.2.dist-info/METADATA
nemony-0.0.2.dist-info/WHEEL
nemony-0.0.2.dist-info/entry_points.txt
nemony-0.0.2.dist-info/top_level.txt
nemony-0.0.2.dist-info/RECORD
