Metadata-Version: 2.1
Name: nemony
Version: 0.0.2
Summary: Convert text to adjective-noun mnemonics.
Author-email: Eachan Johnson <eachan.johnson@crick.ac.uk>
Project-URL: Homepage, https://github.com/scbirlab/nemony
Project-URL: Bug Tracker, https://github.com/scbirlab/nemony/issues
Keywords: mnemonic,hash,programming
Classifier: Development Status :: 3 - Alpha
Classifier: Intended Audience :: Science/Research
Classifier: Topic :: Scientific/Engineering :: Bio-Informatics
Classifier: License :: OSI Approved :: MIT License
Classifier: Programming Language :: Python :: 3.8
Classifier: Programming Language :: Python :: 3.9
Classifier: Programming Language :: Python :: 3.10
Classifier: Programming Language :: Python :: 3.11
Classifier: Programming Language :: Python :: 3 :: Only
Requires-Python: >=3.8
License-File: LICENSE
Requires-Dist: pyyaml
